Metadata-Version: 2.4
Name: evo-data-converters
Version: 0.0.3
License:    Copyright © 2025 Bentley Systems, Incorporated.
Requires-Python: >=3.10
License-File: LICENSE.md
Requires-Dist: aiohttp
Requires-Dist: evo-sdk-common>=0.1.2
Requires-Dist: evo-objects>=0.1.0
Requires-Dist: nest-asyncio
Requires-Dist: numpy<2.0.0
Requires-Dist: omf>=1.0.1
Requires-Dist: omf2>=0.2.0-beta.1
Requires-Dist: pandas==2.2.3
Requires-Dist: pyarrow
Requires-Dist: pure-interface
Requires-Dist: resqpy==5.1.10
Requires-Dist: evo-schemas>=2024.4
Requires-Dist: scipy
Requires-Dist: vtk
Provides-Extra: notebooks
Requires-Dist: evo-sdk-common[notebooks]; extra == "notebooks"
Requires-Dist: authlib; extra == "notebooks"
Requires-Dist: ipykernel; extra == "notebooks"
Requires-Dist: ipython; extra == "notebooks"
Requires-Dist: PyJWT; extra == "notebooks"
Requires-Dist: requests; extra == "notebooks"
Requires-Dist: jupyter; extra == "notebooks"
Dynamic: license-file
